MANIFEST.in
README.txt
setup.py
XStatic_NVD3.egg-info/PKG-INFO
XStatic_NVD3.egg-info/SOURCES.txt
XStatic_NVD3.egg-info/dependency_links.txt
XStatic_NVD3.egg-info/namespace_packages.txt
XStatic_NVD3.egg-info/not-zip-safe
XStatic_NVD3.egg-info/top_level.txt
xstatic/__init__.py
xstatic/pkg/__init__.py
xstatic/pkg/nvd3/__init__.py
xstatic/pkg/nvd3/data/nv.d3.css
xstatic/pkg/nvd3/data/nv.d3.js