Metadata-Version: 1.0
Name: XStatic-NVD3
Version: 1.7.1.0
Summary: NVD3 1.7.1 (XStatic packaging standard)
Home-page: http://nvd3.org/
Author: Thai Tran
Author-email: tqtran@us.ibm.com
License: (same as NVD3)
Keywords: xstatic javascript chart d3 nvd3
Platform: any
